Metadata-Version: 2.1
Name: pycollabim
Version: 1.2
License-File: LICENSE
